[
  {
    "context": "orange",
    "nameSpace": "OHRM",
    "type": "CustomExport",
    "table": "ohrm.hs_hr_custom_export",
    "idSequenceName": "ohrm.hs_hr_custom_export_id_seq",
    "comment": "OHRM Currency Type Map",
    "properties": [
      {
        "name": "code",
        "attr": {
          "type": "Number",
          "column": "code"
        }
      },
      {
        "name": "currency",
        "attr": {
          "type": "String",
          "column": "currency_id"
        }
      },
      {
        "name": "name",
        "attr": {
          "type": "String",
          "column": "currency_name"
        }
      }
    ],
    "isSystem": true
  }
]